MadQt/__init__.py
MadQt/Apps/__init__.py
MadQt/Apps/PluginCreator/__init__.py
MadQt/Apps/PluginCreator/gui.py
MadQt/Apps/PluginCreator/main.py
MadQt/Apps/PluginCreator/myWidgets.py
MadQt/Apps/PluginCreator/pyside6_loader.py
MadQt/Apps/PluginCreator/resources_rc.py
MadQt/Apps/ProjectManager/__init__.py
MadQt/Apps/ProjectManager/gui.py
MadQt/Apps/ProjectManager/gui_new.py
MadQt/Apps/ProjectManager/main.py
MadQt/Apps/ProjectManager/myWidgets.py
MadQt/Apps/ProjectManager/pyside6_loader.py
MadQt/Apps/ProjectManager/resources_rc.py
MadQt/QtDesignerPlugins/__init__.py
MadQt/QtDesignerPlugins/register_all.py
MadQt/QtDesignerPlugins/expander/expander.ico
MadQt/QtDesignerPlugins/expander/expanderplugin.py
MadQt/QtDesignerPlugins/hover_text_button/htbutton.ico
MadQt/QtDesignerPlugins/hover_text_button/htbuttonplugin.py
MadQt/Templates/__init__.py
MadQt/Templates/NewPlugin/__init__.py
MadQt/Templates/NewPlugin/register_template.py
MadQt/Templates/NewPlugin/MultiPage/__init__.py
MadQt/Templates/NewPlugin/MultiPage/template.py
MadQt/Templates/NewPlugin/MultiPage/templateplugin.py
MadQt/Templates/NewPlugin/Simple/__init__.py
MadQt/Templates/NewPlugin/Simple/template.py
MadQt/Templates/NewPlugin/Simple/templateplugin.py
MadQt/Templates/NewPlugin/WithTaskMenu/__init__.py
MadQt/Templates/NewPlugin/WithTaskMenu/template.py
MadQt/Templates/NewPlugin/WithTaskMenu/templateplugin.py
MadQt/Templates/NewProject/main.py
MadQt/Templates/NewProject/gui/__init__.py
MadQt/Templates/NewProject/gui/logo.ico
MadQt/Templates/NewProject/gui/resources.qrc
MadQt/Templates/NewProject/widgets/__init__.py
MadQt/Templates/Uis/mainwindow.ui
MadQt/Templates/Uis/resources.qrc
MadQt/Templates/Uis/widget.ui
MadQt/Tools/__init__.py
MadQt/Tutorials/__init__.py
MadQt/Widgets/__init__.py
MadQt/Widgets/anim_picker.py
MadQt/Widgets/expander.py
MadQt/Widgets/htbutton.py
MadQt/scripts/PluginCreator.py
MadQt/scripts/ProjectManager.py
MadQt/scripts/__init__.py
MadQt-0.0.34.dist-info/LICENSE
MadQt-0.0.34.dist-info/METADATA
MadQt-0.0.34.dist-info/WHEEL
MadQt-0.0.34.dist-info/entry_points.txt
MadQt-0.0.34.dist-info/top_level.txt
MadQt-0.0.34.dist-info/RECORD
