Metadata-Version: 2.1
Name: MadQt
Version: 0.0.34
Summary: Tutorials and Tools for PySide
Home-page: https://github.com/MadPonyInteractive/MadQt
Author: Fabio Goncalves
Author-email: fabiogoncalves@live.co.uk
License: MIT
Classifier: Development Status :: 3 - Alpha
Classifier: License :: OSI Approved :: MIT License
Classifier: Operating System :: OS Independent
Classifier: Programming Language :: Python :: 3.9
Classifier: Programming Language :: Python :: 3.10
Classifier: Natural Language :: English
Classifier: Topic :: Desktop Environment
Classifier: Topic :: Software Development :: Widget Sets
Classifier: Topic :: Education
Requires-Python: >=3.9
License-File: LICENSE
Requires-Dist: PySide6 <=6.4.3,>=6.0.0
Requires-Dist: Pillow >=8.3.0
Requires-Dist: pyinstaller >=4.7
